risclog.zestreleaser.notify-1.1.1-py3.9-nspkg.pth
risclog/zestreleaser/notify/__init__.py
risclog/zestreleaser/notify/config.py
risclog/zestreleaser/notify/conftest.py
risclog/zestreleaser/notify/tests/__init__.py
risclog/zestreleaser/notify/tests/test_config.py
risclog.zestreleaser.notify-1.1.1.dist-info/AUTHORS.rst
risclog.zestreleaser.notify-1.1.1.dist-info/LICENSE
risclog.zestreleaser.notify-1.1.1.dist-info/METADATA
risclog.zestreleaser.notify-1.1.1.dist-info/WHEEL
risclog.zestreleaser.notify-1.1.1.dist-info/entry_points.txt
risclog.zestreleaser.notify-1.1.1.dist-info/namespace_packages.txt
risclog.zestreleaser.notify-1.1.1.dist-info/top_level.txt
risclog.zestreleaser.notify-1.1.1.dist-info/RECORD
