Metadata-Version: 2.1
Name: risclog.zestreleaser.notify
Version: 1.1.1
Summary: Notify about new release in keybase channel.
Home-page: https://github.com/risclog-solution/risclog.zestreleaser.notify
Author: riscLOG Solution GmbH
Author-email: info@risclog.de
License: MIT license
Keywords: risclog.zestreleaser.notify
Classifier: Development Status :: 2 - Pre-Alpha
Classifier: Intended Audience :: Developers
Classifier: License :: OSI Approved :: MIT License
Classifier: Natural Language :: German
Classifier: Programming Language :: Python :: 3
Classifier: Programming Language :: Python :: 3.6
Classifier: Programming Language :: Python :: 3.7
Classifier: Programming Language :: Python :: 3.8
Requires-Python: >=3.6
License-File: LICENSE
License-File: AUTHORS.rst
Requires-Dist: pydantic[dotenv] <2
Requires-Dist: zest.releaser >=5.0
Requires-Dist: requests
Requires-Dist: six
Provides-Extra: docs
Requires-Dist: Sphinx ; extra == 'docs'
Provides-Extra: test
Requires-Dist: pytest-cache ; extra == 'test'
Requires-Dist: pytest-cov ; extra == 'test'
Requires-Dist: pytest-flake8 ; extra == 'test'
Requires-Dist: pytest-rerunfailures ; extra == 'test'
Requires-Dist: pytest-sugar ; extra == 'test'
Requires-Dist: pytest ; extra == 'test'
Requires-Dist: coverage ; extra == 'test'
Requires-Dist: flake8 <4 ; extra == 'test'
Requires-Dist: mock ; extra == 'test'
Requires-Dist: requests ; extra == 'test'
